blockbrain_api/__init__.py
blockbrain_api/api.py
blockbrain_api/chat.py
blockbrain_api/core.py
blockbrain_api-0.1.3.dist-info/licenses/LICENSE
blockbrain_api-0.1.3.dist-info/METADATA
blockbrain_api-0.1.3.dist-info/WHEEL
blockbrain_api-0.1.3.dist-info/top_level.txt
blockbrain_api-0.1.3.dist-info/RECORD
