Metadata-Version: 2.4
Name: blockbrain-api
Version: 0.1.3
Summary: A Python client for the BlockBrain API with model selection, chat, file upload, and streaming support
Home-page: https://github.com/blockbrain/blockbrain-api-python
Author: BlockBrain
Author-email: BlockBrain <support@blockbrain.ai>
License: MIT
Project-URL: Homepage, https://github.com/blockbrain/blockbrain-api-python
Project-URL: Documentation, https://docs.blockbrain.ai
Project-URL: Repository, https://github.com/blockbrain/blockbrain-api-python
Project-URL: Bug Reports, https://github.com/blockbrain/blockbrain-api-python/issues
Keywords: blockbrain,api,chat,ai,streaming,nlp,model-selection,llm
Classifier: Development Status :: 3 - Alpha
Classifier: Intended Audience :: Developers
Classifier: License :: OSI Approved :: MIT License
Classifier: Operating System :: OS Independent
Classifier: Programming Language :: Python :: 3
Classifier: Programming Language :: Python :: 3.8
Classifier: Programming Language :: Python :: 3.9
Classifier: Programming Language :: Python :: 3.10
Classifier: Programming Language :: Python :: 3.11
Classifier: Programming Language :: Python :: 3.12
Classifier: Topic :: Software Development :: Libraries :: Python Modules
Classifier: Topic :: Internet :: WWW/HTTP :: Dynamic Content
Classifier: Topic :: Scientific/Engineering :: Artificial Intelligence
Requires-Python: >=3.7
License-File: LICENSE
Requires-Dist: requests>=2.25.0
Provides-Extra: dev
Requires-Dist: pytest>=6.0; extra == "dev"
Requires-Dist: pytest-cov; extra == "dev"
Requires-Dist: black; extra == "dev"
Requires-Dist: flake8; extra == "dev"
Requires-Dist: mypy; extra == "dev"
Dynamic: author
Dynamic: home-page
Dynamic: license-file
Dynamic: requires-python
